globlin-0.2.0.dist-info/METADATA
globlin-0.2.0.dist-info/WHEEL
globlin-0.2.0.dist-info/licenses/LICENSE
globlin/__init__.py
globlin/globlin.abi3.so
globlin/globlin.pyi
globlin/py.typed
globlin-0.2.0.dist-info/RECORD
