Metadata-Version: 2.4
Name: globlin
Version: 0.2.0
Classifier: Programming Language :: Rust
Classifier: Programming Language :: Python :: Implementation :: CPython
Classifier: Programming Language :: Python :: Implementation :: PyPy
License-File: LICENSE
Summary: A featureful fnmatch implementation
License-Expression: EUPL-1.2
Requires-Python: >=3.10
Project-URL: Homepage, https://vlaci.github.io/globlin
Project-URL: Repository, https://github.com/vlaci/globlin
Project-URL: Changelog, https://github.com/vlaci/globlin/blob/main/CHANGELOG.md
